codearc/__init__.py
codearc/cli.py
codearc/database.py
codearc/py.typed
codearc/utils.py
codearc/extraction/__init__.py
codearc/extraction/docstring.py
codearc/extraction/extract_symbols.py
codearc/extraction/symbol_extractor.py
codearc/mining/__init__.py
codearc/mining/encoding_config.py
codearc/mining/ignore_patterns.py
codearc/mining/miner.py
codearc/mining/mining_config.py
codearc/mining/mining_stats.py
codearc/mining/symbol_version.py
codearc/models/__init__.py
codearc/models/extracted_symbol.py
codearc-0.1.0.dist-info/METADATA
codearc-0.1.0.dist-info/WHEEL
codearc-0.1.0.dist-info/entry_points.txt
codearc-0.1.0.dist-info/licenses/LICENSE
codearc-0.1.0.dist-info/RECORD
