Metadata-Version: 2.4
Name: codearc
Version: 0.1.0
Summary: Mine a Python repo's git history to produce a DuckDB database of all distinct versions of every function/class
Project-URL: Repository, https://github.com/drothermel/codearc
Project-URL: Issues, https://github.com/drothermel/codearc/issues
Author-email: Danielle Rothermel <danielle.rothermel@gmail.com>
License-Expression: MIT
License-File: LICENSE
Keywords: ast,code-analysis,duckdb,git,history,mining,python
Classifier: Development Status :: 4 - Beta
Classifier: Environment :: Console
Classifier: Intended Audience :: Developers
Classifier: License :: OSI Approved :: MIT License
Classifier: Programming Language :: Python :: 3.12
Classifier: Topic :: Software Development :: Libraries :: Python Modules
Classifier: Topic :: Software Development :: Version Control :: Git
Requires-Python: >=3.12
Requires-Dist: duckdb>=0.10
Requires-Dist: libcst>=1.1
Requires-Dist: pydantic>=2.0
Requires-Dist: pydriller>=2.6
Requires-Dist: rich>=13.0
Requires-Dist: typer>=0.12
